notification_service/__init__.py
notification_service/__main__.py
notification_service/alembic.ini
notification_service/settings.py
notification_service/version.py
notification_service/cli/__init__.py
notification_service/cli/cli_parser.py
notification_service/cli/simple_table.py
notification_service/cli/commands/__init__.py
notification_service/cli/commands/config_command.py
notification_service/cli/commands/db_command.py
notification_service/cli/commands/event_command.py
notification_service/cli/commands/server_command.py
notification_service/cli/commands/version_command.py
notification_service/client/__init__.py
notification_service/client/embedded_notification_client.py
notification_service/client/notification_client.py
notification_service/config_templates/__init__.py
notification_service/config_templates/default_notification_server.yaml
notification_service/migrations/__init__.py
notification_service/migrations/env.py
notification_service/migrations/versions/29623a4151ed_add_member.py
notification_service/migrations/versions/87cb292bcc31_add_tables.py
notification_service/migrations/versions/__init__.py
notification_service/model/__init__.py
notification_service/model/event.py
notification_service/model/member.py
notification_service/model/sender_event_count.py
notification_service/rpc/__init__.py
notification_service/rpc/service.py
notification_service/rpc/protobuf/__init__.py
notification_service/rpc/protobuf/notification_service_pb2.py
notification_service/rpc/protobuf/notification_service_pb2_grpc.py
notification_service/server/__init__.py
notification_service/server/ha_manager.py
notification_service/server/server.py
notification_service/server/server_runner.py
notification_service/storage/__init__.py
notification_service/storage/event_storage.py
notification_service/storage/high_availability.py
notification_service/storage/alchemy/__init__.py
notification_service/storage/alchemy/base.py
notification_service/storage/alchemy/db_client_storage.py
notification_service_nightly-2023.12.31.dist-info/METADATA
notification_service_nightly-2023.12.31.dist-info/WHEEL
notification_service_nightly-2023.12.31.dist-info/entry_points.txt
notification_service_nightly-2023.12.31.dist-info/top_level.txt
notification_service_nightly-2023.12.31.dist-info/RECORD
